pqquotation/__init__.py
pqquotation/api.py
pqquotation/basequotation.py
pqquotation/boc.py
pqquotation/config.py
pqquotation/daykline.py
pqquotation/dc.py
pqquotation/helpers.py
pqquotation/hkquote.py
pqquotation/jsl.py
pqquotation/roundrobin.py
pqquotation/rtq.py
pqquotation/sina.py
pqquotation/stock_codes.conf
pqquotation/tencent.py
pqquotation-0.8.4.dist-info/licenses/LICENSE
pqquotation-0.8.4.dist-info/METADATA
pqquotation-0.8.4.dist-info/WHEEL
pqquotation-0.8.4.dist-info/top_level.txt
pqquotation-0.8.4.dist-info/RECORD
