Metadata-Version: 2.4
Name: pqquotation
Version: 0.8.4
Summary: A utility for Fetch China Stock Info
Home-page: https://github.com/bushuhui/pqquotation
Author: bushuhui
Author-email: bushuhui@foxmail.com
License: BSD
Keywords: China stock trade
Classifier: Development Status :: 4 - Beta
Classifier: Programming Language :: Python :: 3.5
Classifier: License :: OSI Approved :: BSD License
Requires-Python: >=3.6
License-File: LICENSE
Requires-Dist: requests
Dynamic: author
Dynamic: author-email
Dynamic: classifier
Dynamic: description
Dynamic: description-content-type
Dynamic: home-page
Dynamic: keywords
Dynamic: license
Dynamic: license-file
Dynamic: requires-dist
Dynamic: requires-python
Dynamic: summary
